{"nodes": [{"id": "d_casa_atreides_api_book_coffee_shop_internal_usecase_company_usecase_go", "label": "company_usecase.go", "file_type": "code", "source_file": "internal/usecase/company_usecase.go", "source_location": "L1"}, {"id": "usecase_companyusecase", "label": "CompanyUseCase", "file_type": "code", "source_file": "internal/usecase/company_usecase.go", "source_location": "L11"}, {"id": "companyrepository", "label": "CompanyRepository", "file_type": "code", "source_file": "internal/usecase/company_usecase.go", "source_location": "L21"}, {"id": "usecase_company_usecase_newcompanyusecase", "label": "NewCompanyUseCase()", "file_type": "code", "source_file": "internal/usecase/company_usecase.go", "source_location": "L24"}, {"id": "usecase_companyusecase_create", "label": ".Create()", "file_type": "code", "source_file": "internal/usecase/company_usecase.go", "source_location": "L28"}, {"id": "userid", "label": "userID", "file_type": "code", "source_file": "internal/usecase/company_usecase.go", "source_location": "L28"}, {"id": "nit", "label": "nit", "file_type": "code", "source_file": "internal/usecase/company_usecase.go", "source_location": "L28"}, {"id": "socialreason", "label": "socialReason", "file_type": "code", "source_file": "internal/usecase/company_usecase.go", "source_location": "L28"}, {"id": "company", "label": "Company", "file_type": "code", "source_file": "internal/usecase/company_usecase.go", "source_location": "L28"}, {"id": "usecase_companyusecase_getbyuserid", "label": ".GetByUserID()", "file_type": "code", "source_file": "internal/usecase/company_usecase.go", "source_location": "L61"}, {"id": "usecase_companyusecase_getbyid", "label": ".GetByID()", "file_type": "code", "source_file": "internal/usecase/company_usecase.go", "source_location": "L68"}, {"id": "usecase_companyusecase_getall", "label": ".GetAll()", "file_type": "code", "source_file": "internal/usecase/company_usecase.go", "source_location": "L75"}, {"id": "usecase_companyusecase_update", "label": ".Update()", "file_type": "code", "source_file": "internal/usecase/company_usecase.go", "source_location": "L79"}, {"id": "id", "label": "id", "file_type": "code", "source_file": "internal/usecase/company_usecase.go", "source_location": "L79"}, {"id": "usecase_companyusecase_delete", "label": ".Delete()", "file_type": "code", "source_file": "internal/usecase/company_usecase.go", "source_location": "L116"}, {"id": "usecase_company_usecase_validatecompanyfields", "label": "validateCompanyFields()", "file_type": "code", "source_file": "internal/usecase/company_usecase.go", "source_location": "L123"}], "edges": [{"source": "d_casa_atreides_api_book_coffee_shop_internal_usecase_company_usecase_go", "target": "go_pkg_errors", "relation": "imports_from", "confidence": "EXTRACTED", "source_file": "internal/usecase/company_usecase.go", "source_location": "L4", "weight": 1.0, "context": "import"}, {"source": "d_casa_atreides_api_book_coffee_shop_internal_usecase_company_usecase_go", "target": "go_pkg_time", "relation": "imports_from", "confidence": "EXTRACTED", "source_file": "internal/usecase/company_usecase.go", "source_location": "L5", "weight": 1.0, "context": "import"}, {"source": "d_casa_atreides_api_book_coffee_shop_internal_usecase_company_usecase_go", "target": "go_pkg_book_coffee_shop_internal_domain", "relation": "imports_from", "confidence": "EXTRACTED", "source_file": "internal/usecase/company_usecase.go", "source_location": "L7", "weight": 1.0, "context": "import"}, {"source": "d_casa_atreides_api_book_coffee_shop_internal_usecase_company_usecase_go", "target": "go_pkg_book_coffee_shop_internal_repository", "relation": "imports_from", "confidence": "EXTRACTED", "source_file": "internal/usecase/company_usecase.go", "source_location": "L8", "weight": 1.0, "context": "import"}, {"source": "d_casa_atreides_api_book_coffee_shop_internal_usecase_company_usecase_go", "target": "usecase_companyusecase", "relation": "contains", "confidence": "EXTRACTED", "source_file": "internal/usecase/company_usecase.go", "source_location": "L11", "weight": 1.0}, {"source": "d_casa_atreides_api_book_coffee_shop_internal_usecase_company_usecase_go", "target": "usecase_companyusecase", "relation": "contains", "confidence": "EXTRACTED", "source_file": "internal/usecase/company_usecase.go", "source_location": "L20", "weight": 1.0}, {"source": "usecase_companyusecase", "target": "companyrepository", "relation": "references", "confidence": "EXTRACTED", "source_file": "internal/usecase/company_usecase.go", "source_location": "L21", "weight": 1.0, "context": "field"}, {"source": "d_casa_atreides_api_book_coffee_shop_internal_usecase_company_usecase_go", "target": "usecase_company_usecase_newcompanyusecase", "relation": "contains", "confidence": "EXTRACTED", "source_file": "internal/usecase/company_usecase.go", "source_location": "L24", "weight": 1.0}, {"source": "usecase_company_usecase_newcompanyusecase", "target": "companyrepository", "relation": "references", "confidence": "EXTRACTED", "source_file": "internal/usecase/company_usecase.go", "source_location": "L24", "weight": 1.0, "context": "parameter_type"}, {"source": "usecase_company_usecase_newcompanyusecase", "target": "usecase_companyusecase", "relation": "references", "confidence": "EXTRACTED", "source_file": "internal/usecase/company_usecase.go", "source_location": "L24", "weight": 1.0, "context": "return_type"}, {"source": "usecase_companyusecase", "target": "usecase_companyusecase_create", "relation": "method", "confidence": "EXTRACTED", "source_file": "internal/usecase/company_usecase.go", "source_location": "L28", "weight": 1.0}, {"source": "usecase_companyusecase_create", "target": "userid", "relation": "references", "confidence": "EXTRACTED", "source_file": "internal/usecase/company_usecase.go", "source_location": "L28", "weight": 1.0, "context": "parameter_type"}, {"source": "usecase_companyusecase_create", "target": "nit", "relation": "references", "confidence": "EXTRACTED", "source_file": "internal/usecase/company_usecase.go", "source_location": "L28", "weight": 1.0, "context": "parameter_type"}, {"source": "usecase_companyusecase_create", "target": "socialreason", "relation": "references", "confidence": "EXTRACTED", "source_file": "internal/usecase/company_usecase.go", "source_location": "L28", "weight": 1.0, "context": "parameter_type"}, {"source": "usecase_companyusecase_create", "target": "company", "relation": "references", "confidence": "EXTRACTED", "source_file": "internal/usecase/company_usecase.go", "source_location": "L28", "weight": 1.0, "context": "return_type"}, {"source": "usecase_companyusecase", "target": "usecase_companyusecase_getbyuserid", "relation": "method", "confidence": "EXTRACTED", "source_file": "internal/usecase/company_usecase.go", "source_location": "L61", "weight": 1.0}, {"source": "usecase_companyusecase_getbyuserid", "target": "company", "relation": "references", "confidence": "EXTRACTED", "source_file": "internal/usecase/company_usecase.go", "source_location": "L61", "weight": 1.0, "context": "return_type"}, {"source": "usecase_companyusecase", "target": "usecase_companyusecase_getbyid", "relation": "method", "confidence": "EXTRACTED", "source_file": "internal/usecase/company_usecase.go", "source_location": "L68", "weight": 1.0}, {"source": "usecase_companyusecase_getbyid", "target": "company", "relation": "references", "confidence": "EXTRACTED", "source_file": "internal/usecase/company_usecase.go", "source_location": "L68", "weight": 1.0, "context": "return_type"}, {"source": "usecase_companyusecase", "target": "usecase_companyusecase_getall", "relation": "method", "confidence": "EXTRACTED", "source_file": "internal/usecase/company_usecase.go", "source_location": "L75", "weight": 1.0}, {"source": "usecase_companyusecase_getall", "target": "company", "relation": "references", "confidence": "EXTRACTED", "source_file": "internal/usecase/company_usecase.go", "source_location": "L75", "weight": 1.0, "context": "return_type"}, {"source": "usecase_companyusecase", "target": "usecase_companyusecase_update", "relation": "method", "confidence": "EXTRACTED", "source_file": "internal/usecase/company_usecase.go", "source_location": "L79", "weight": 1.0}, {"source": "usecase_companyusecase_update", "target": "id", "relation": "references", "confidence": "EXTRACTED", "source_file": "internal/usecase/company_usecase.go", "source_location": "L79", "weight": 1.0, "context": "parameter_type"}, {"source": "usecase_companyusecase_update", "target": "userid", "relation": "references", "confidence": "EXTRACTED", "source_file": "internal/usecase/company_usecase.go", "source_location": "L79", "weight": 1.0, "context": "parameter_type"}, {"source": "usecase_companyusecase_update", "target": "nit", "relation": "references", "confidence": "EXTRACTED", "source_file": "internal/usecase/company_usecase.go", "source_location": "L79", "weight": 1.0, "context": "parameter_type"}, {"source": "usecase_companyusecase_update", "target": "socialreason", "relation": "references", "confidence": "EXTRACTED", "source_file": "internal/usecase/company_usecase.go", "source_location": "L79", "weight": 1.0, "context": "parameter_type"}, {"source": "usecase_companyusecase_update", "target": "company", "relation": "references", "confidence": "EXTRACTED", "source_file": "internal/usecase/company_usecase.go", "source_location": "L79", "weight": 1.0, "context": "return_type"}, {"source": "usecase_companyusecase", "target": "usecase_companyusecase_delete", "relation": "method", "confidence": "EXTRACTED", "source_file": "internal/usecase/company_usecase.go", "source_location": "L116", "weight": 1.0}, {"source": "d_casa_atreides_api_book_coffee_shop_internal_usecase_company_usecase_go", "target": "usecase_company_usecase_validatecompanyfields", "relation": "contains", "confidence": "EXTRACTED", "source_file": "internal/usecase/company_usecase.go", "source_location": "L123", "weight": 1.0}, {"source": "usecase_companyusecase_create", "target": "usecase_company_usecase_validatecompanyfields", "relation": "calls", "context": "call", "confidence": "EXTRACTED", "source_file": "internal/usecase/company_usecase.go", "source_location": "L29", "weight": 1.0}, {"source": "usecase_companyusecase_update", "target": "usecase_company_usecase_validatecompanyfields", "relation": "calls", "context": "call", "confidence": "EXTRACTED", "source_file": "internal/usecase/company_usecase.go", "source_location": "L83", "weight": 1.0}, {"source": "usecase_companyusecase_update", "target": "usecase_companyusecase_getbyid", "relation": "calls", "context": "call", "confidence": "EXTRACTED", "source_file": "internal/usecase/company_usecase.go", "source_location": "L87", "weight": 1.0}], "raw_calls": [{"caller_nid": "usecase_companyusecase_create", "callee": "GetByNIT", "is_member_call": true, "source_file": "D:\\Casa-Atreides\\api-book-coffee-shop\\internal\\usecase\\company_usecase.go", "source_location": "L33"}, {"caller_nid": "usecase_companyusecase_create", "callee": "New", "is_member_call": false, "source_file": "D:\\Casa-Atreides\\api-book-coffee-shop\\internal\\usecase\\company_usecase.go", "source_location": "L34"}, {"caller_nid": "usecase_companyusecase_create", "callee": "generateID", "is_member_call": false, "source_file": "D:\\Casa-Atreides\\api-book-coffee-shop\\internal\\usecase\\company_usecase.go", "source_location": "L38"}, {"caller_nid": "usecase_companyusecase_create", "callee": "Now", "is_member_call": false, "source_file": "D:\\Casa-Atreides\\api-book-coffee-shop\\internal\\usecase\\company_usecase.go", "source_location": "L51"}, {"caller_nid": "usecase_companyusecase_create", "callee": "Now", "is_member_call": false, "source_file": "D:\\Casa-Atreides\\api-book-coffee-shop\\internal\\usecase\\company_usecase.go", "source_location": "L52"}, {"caller_nid": "usecase_companyusecase_create", "callee": "Create", "is_member_call": true, "source_file": "D:\\Casa-Atreides\\api-book-coffee-shop\\internal\\usecase\\company_usecase.go", "source_location": "L55"}, {"caller_nid": "usecase_companyusecase_getbyuserid", "callee": "New", "is_member_call": false, "source_file": "D:\\Casa-Atreides\\api-book-coffee-shop\\internal\\usecase\\company_usecase.go", "source_location": "L63"}, {"caller_nid": "usecase_companyusecase_getbyuserid", "callee": "GetByUserID", "is_member_call": true, "source_file": "D:\\Casa-Atreides\\api-book-coffee-shop\\internal\\usecase\\company_usecase.go", "source_location": "L65"}, {"caller_nid": "usecase_companyusecase_getbyid", "callee": "New", "is_member_call": false, "source_file": "D:\\Casa-Atreides\\api-book-coffee-shop\\internal\\usecase\\company_usecase.go", "source_location": "L70"}, {"caller_nid": "usecase_companyusecase_getbyid", "callee": "GetByID", "is_member_call": true, "source_file": "D:\\Casa-Atreides\\api-book-coffee-shop\\internal\\usecase\\company_usecase.go", "source_location": "L72"}, {"caller_nid": "usecase_companyusecase_getall", "callee": "GetAll", "is_member_call": true, "source_file": "D:\\Casa-Atreides\\api-book-coffee-shop\\internal\\usecase\\company_usecase.go", "source_location": "L76"}, {"caller_nid": "usecase_companyusecase_update", "callee": "New", "is_member_call": false, "source_file": "D:\\Casa-Atreides\\api-book-coffee-shop\\internal\\usecase\\company_usecase.go", "source_location": "L81"}, {"caller_nid": "usecase_companyusecase_update", "callee": "GetByNIT", "is_member_call": true, "source_file": "D:\\Casa-Atreides\\api-book-coffee-shop\\internal\\usecase\\company_usecase.go", "source_location": "L92"}, {"caller_nid": "usecase_companyusecase_update", "callee": "New", "is_member_call": false, "source_file": "D:\\Casa-Atreides\\api-book-coffee-shop\\internal\\usecase\\company_usecase.go", "source_location": "L93"}, {"caller_nid": "usecase_companyusecase_update", "callee": "Now", "is_member_call": false, "source_file": "D:\\Casa-Atreides\\api-book-coffee-shop\\internal\\usecase\\company_usecase.go", "source_location": "L108"}, {"caller_nid": "usecase_companyusecase_update", "callee": "Update", "is_member_call": true, "source_file": "D:\\Casa-Atreides\\api-book-coffee-shop\\internal\\usecase\\company_usecase.go", "source_location": "L110"}, {"caller_nid": "usecase_companyusecase_delete", "callee": "New", "is_member_call": false, "source_file": "D:\\Casa-Atreides\\api-book-coffee-shop\\internal\\usecase\\company_usecase.go", "source_location": "L118"}, {"caller_nid": "usecase_companyusecase_delete", "callee": "Delete", "is_member_call": true, "source_file": "D:\\Casa-Atreides\\api-book-coffee-shop\\internal\\usecase\\company_usecase.go", "source_location": "L120"}, {"caller_nid": "usecase_company_usecase_validatecompanyfields", "callee": "New", "is_member_call": false, "source_file": "D:\\Casa-Atreides\\api-book-coffee-shop\\internal\\usecase\\company_usecase.go", "source_location": "L125"}, {"caller_nid": "usecase_company_usecase_validatecompanyfields", "callee": "New", "is_member_call": false, "source_file": "D:\\Casa-Atreides\\api-book-coffee-shop\\internal\\usecase\\company_usecase.go", "source_location": "L128"}, {"caller_nid": "usecase_company_usecase_validatecompanyfields", "callee": "New", "is_member_call": false, "source_file": "D:\\Casa-Atreides\\api-book-coffee-shop\\internal\\usecase\\company_usecase.go", "source_location": "L131"}, {"caller_nid": "usecase_company_usecase_validatecompanyfields", "callee": "New", "is_member_call": false, "source_file": "D:\\Casa-Atreides\\api-book-coffee-shop\\internal\\usecase\\company_usecase.go", "source_location": "L134"}, {"caller_nid": "usecase_company_usecase_validatecompanyfields", "callee": "New", "is_member_call": false, "source_file": "D:\\Casa-Atreides\\api-book-coffee-shop\\internal\\usecase\\company_usecase.go", "source_location": "L137"}, {"caller_nid": "usecase_company_usecase_validatecompanyfields", "callee": "New", "is_member_call": false, "source_file": "D:\\Casa-Atreides\\api-book-coffee-shop\\internal\\usecase\\company_usecase.go", "source_location": "L140"}, {"caller_nid": "usecase_company_usecase_validatecompanyfields", "callee": "New", "is_member_call": false, "source_file": "D:\\Casa-Atreides\\api-book-coffee-shop\\internal\\usecase\\company_usecase.go", "source_location": "L143"}]}