{"nodes": [{"id": "d_go_api_book_coffee_shop_internal_usecase_shipment_usecase_go", "label": "shipment_usecase.go", "file_type": "code", "source_file": "internal/usecase/shipment_usecase.go", "source_location": "L1"}, {"id": "usecase_shipmentusecase", "label": "ShipmentUseCase", "file_type": "code", "source_file": "internal/usecase/shipment_usecase.go", "source_location": "L17"}, {"id": "db", "label": "DB", "file_type": "code", "source_file": "internal/usecase/shipment_usecase.go", "source_location": "L26"}, {"id": "shipmentrepository", "label": "ShipmentRepository", "file_type": "code", "source_file": "internal/usecase/shipment_usecase.go", "source_location": "L27"}, {"id": "shipmentrepofactory", "label": "ShipmentRepoFactory", "file_type": "code", "source_file": "internal/usecase/shipment_usecase.go", "source_location": "L28"}, {"id": "historyservice", "label": "HistoryService", "file_type": "code", "source_file": "internal/usecase/shipment_usecase.go", "source_location": "L29"}, {"id": "usecase_shipment_usecase_newshipmentusecase", "label": "NewShipmentUseCase()", "file_type": "code", "source_file": "internal/usecase/shipment_usecase.go", "source_location": "L32"}, {"id": "usecase_shipmentusecase_create", "label": ".Create()", "file_type": "code", "source_file": "internal/usecase/shipment_usecase.go", "source_location": "L36"}, {"id": "sourcedocument", "label": "SourceDocument", "file_type": "code", "source_file": "internal/usecase/shipment_usecase.go", "source_location": "L36"}, {"id": "recipient", "label": "Recipient", "file_type": "code", "source_file": "internal/usecase/shipment_usecase.go", "source_location": "L36"}, {"id": "shipmentdetail", "label": "ShipmentDetail", "file_type": "code", "source_file": "internal/usecase/shipment_usecase.go", "source_location": "L36"}, {"id": "shipmentfinancialsummary", "label": "ShipmentFinancialSummary", "file_type": "code", "source_file": "internal/usecase/shipment_usecase.go", "source_location": "L36"}, {"id": "shipment", "label": "Shipment", "file_type": "code", "source_file": "internal/usecase/shipment_usecase.go", "source_location": "L36"}, {"id": "usecase_shipmentusecase_getbyid", "label": ".GetByID()", "file_type": "code", "source_file": "internal/usecase/shipment_usecase.go", "source_location": "L92"}, {"id": "usecase_shipmentusecase_getall", "label": ".GetAll()", "file_type": "code", "source_file": "internal/usecase/shipment_usecase.go", "source_location": "L99"}, {"id": "usecase_shipmentusecase_update", "label": ".Update()", "file_type": "code", "source_file": "internal/usecase/shipment_usecase.go", "source_location": "L103"}, {"id": "usecase_shipmentusecase_delete", "label": ".Delete()", "file_type": "code", "source_file": "internal/usecase/shipment_usecase.go", "source_location": "L157"}, {"id": "usecase_shipment_usecase_validateshipmentfields", "label": "validateShipmentFields()", "file_type": "code", "source_file": "internal/usecase/shipment_usecase.go", "source_location": "L193"}], "edges": [{"source": "d_go_api_book_coffee_shop_internal_usecase_shipment_usecase_go", "target": "go_pkg_database_sql", "relation": "imports_from", "confidence": "EXTRACTED", "source_file": "internal/usecase/shipment_usecase.go", "source_location": "L4", "weight": 1.0, "context": "import"}, {"source": "d_go_api_book_coffee_shop_internal_usecase_shipment_usecase_go", "target": "go_pkg_errors", "relation": "imports_from", "confidence": "EXTRACTED", "source_file": "internal/usecase/shipment_usecase.go", "source_location": "L5", "weight": 1.0, "context": "import"}, {"source": "d_go_api_book_coffee_shop_internal_usecase_shipment_usecase_go", "target": "go_pkg_slices", "relation": "imports_from", "confidence": "EXTRACTED", "source_file": "internal/usecase/shipment_usecase.go", "source_location": "L6", "weight": 1.0, "context": "import"}, {"source": "d_go_api_book_coffee_shop_internal_usecase_shipment_usecase_go", "target": "go_pkg_time", "relation": "imports_from", "confidence": "EXTRACTED", "source_file": "internal/usecase/shipment_usecase.go", "source_location": "L7", "weight": 1.0, "context": "import"}, {"source": "d_go_api_book_coffee_shop_internal_usecase_shipment_usecase_go", "target": "go_pkg_book_coffee_shop_internal_domain", "relation": "imports_from", "confidence": "EXTRACTED", "source_file": "internal/usecase/shipment_usecase.go", "source_location": "L9", "weight": 1.0, "context": "import"}, {"source": "d_go_api_book_coffee_shop_internal_usecase_shipment_usecase_go", "target": "go_pkg_book_coffee_shop_internal_repository", "relation": "imports_from", "confidence": "EXTRACTED", "source_file": "internal/usecase/shipment_usecase.go", "source_location": "L10", "weight": 1.0, "context": "import"}, {"source": "d_go_api_book_coffee_shop_internal_usecase_shipment_usecase_go", "target": "usecase_shipmentusecase", "relation": "contains", "confidence": "EXTRACTED", "source_file": "internal/usecase/shipment_usecase.go", "source_location": "L17", "weight": 1.0}, {"source": "d_go_api_book_coffee_shop_internal_usecase_shipment_usecase_go", "target": "usecase_shipmentusecase", "relation": "contains", "confidence": "EXTRACTED", "source_file": "internal/usecase/shipment_usecase.go", "source_location": "L25", "weight": 1.0}, {"source": "usecase_shipmentusecase", "target": "db", "relation": "references", "confidence": "EXTRACTED", "source_file": "internal/usecase/shipment_usecase.go", "source_location": "L26", "weight": 1.0, "context": "field"}, {"source": "usecase_shipmentusecase", "target": "shipmentrepository", "relation": "references", "confidence": "EXTRACTED", "source_file": "internal/usecase/shipment_usecase.go", "source_location": "L27", "weight": 1.0, "context": "field"}, {"source": "usecase_shipmentusecase", "target": "shipmentrepofactory", "relation": "references", "confidence": "EXTRACTED", "source_file": "internal/usecase/shipment_usecase.go", "source_location": "L28", "weight": 1.0, "context": "field"}, {"source": "usecase_shipmentusecase", "target": "historyservice", "relation": "references", "confidence": "EXTRACTED", "source_file": "internal/usecase/shipment_usecase.go", "source_location": "L29", "weight": 1.0, "context": "field"}, {"source": "d_go_api_book_coffee_shop_internal_usecase_shipment_usecase_go", "target": "usecase_shipment_usecase_newshipmentusecase", "relation": "contains", "confidence": "EXTRACTED", "source_file": "internal/usecase/shipment_usecase.go", "source_location": "L32", "weight": 1.0}, {"source": "usecase_shipment_usecase_newshipmentusecase", "target": "db", "relation": "references", "confidence": "EXTRACTED", "source_file": "internal/usecase/shipment_usecase.go", "source_location": "L32", "weight": 1.0, "context": "parameter_type"}, {"source": "usecase_shipment_usecase_newshipmentusecase", "target": "shipmentrepository", "relation": "references", "confidence": "EXTRACTED", "source_file": "internal/usecase/shipment_usecase.go", "source_location": "L32", "weight": 1.0, "context": "parameter_type"}, {"source": "usecase_shipment_usecase_newshipmentusecase", "target": "shipmentrepofactory", "relation": "references", "confidence": "EXTRACTED", "source_file": "internal/usecase/shipment_usecase.go", "source_location": "L32", "weight": 1.0, "context": "parameter_type"}, {"source": "usecase_shipment_usecase_newshipmentusecase", "target": "historyservice", "relation": "references", "confidence": "EXTRACTED", "source_file": "internal/usecase/shipment_usecase.go", "source_location": "L32", "weight": 1.0, "context": "parameter_type"}, {"source": "usecase_shipment_usecase_newshipmentusecase", "target": "usecase_shipmentusecase", "relation": "references", "confidence": "EXTRACTED", "source_file": "internal/usecase/shipment_usecase.go", "source_location": "L32", "weight": 1.0, "context": "return_type"}, {"source": "usecase_shipmentusecase", "target": "usecase_shipmentusecase_create", "relation": "method", "confidence": "EXTRACTED", "source_file": "internal/usecase/shipment_usecase.go", "source_location": "L36", "weight": 1.0}, {"source": "usecase_shipmentusecase_create", "target": "sourcedocument", "relation": "references", "confidence": "EXTRACTED", "source_file": "internal/usecase/shipment_usecase.go", "source_location": "L36", "weight": 1.0, "context": "parameter_type"}, {"source": "usecase_shipmentusecase_create", "target": "recipient", "relation": "references", "confidence": "EXTRACTED", "source_file": "internal/usecase/shipment_usecase.go", "source_location": "L36", "weight": 1.0, "context": "parameter_type"}, {"source": "usecase_shipmentusecase_create", "target": "shipmentdetail", "relation": "references", "confidence": "EXTRACTED", "source_file": "internal/usecase/shipment_usecase.go", "source_location": "L36", "weight": 1.0, "context": "parameter_type"}, {"source": "usecase_shipmentusecase_create", "target": "shipmentfinancialsummary", "relation": "references", "confidence": "EXTRACTED", "source_file": "internal/usecase/shipment_usecase.go", "source_location": "L36", "weight": 1.0, "context": "parameter_type"}, {"source": "usecase_shipmentusecase_create", "target": "shipment", "relation": "references", "confidence": "EXTRACTED", "source_file": "internal/usecase/shipment_usecase.go", "source_location": "L36", "weight": 1.0, "context": "return_type"}, {"source": "usecase_shipmentusecase", "target": "usecase_shipmentusecase_getbyid", "relation": "method", "confidence": "EXTRACTED", "source_file": "internal/usecase/shipment_usecase.go", "source_location": "L92", "weight": 1.0}, {"source": "usecase_shipmentusecase_getbyid", "target": "shipment", "relation": "references", "confidence": "EXTRACTED", "source_file": "internal/usecase/shipment_usecase.go", "source_location": "L92", "weight": 1.0, "context": "return_type"}, {"source": "usecase_shipmentusecase", "target": "usecase_shipmentusecase_getall", "relation": "method", "confidence": "EXTRACTED", "source_file": "internal/usecase/shipment_usecase.go", "source_location": "L99", "weight": 1.0}, {"source": "usecase_shipmentusecase_getall", "target": "shipment", "relation": "references", "confidence": "EXTRACTED", "source_file": "internal/usecase/shipment_usecase.go", "source_location": "L99", "weight": 1.0, "context": "return_type"}, {"source": "usecase_shipmentusecase", "target": "usecase_shipmentusecase_update", "relation": "method", "confidence": "EXTRACTED", "source_file": "internal/usecase/shipment_usecase.go", "source_location": "L103", "weight": 1.0}, {"source": "usecase_shipmentusecase_update", "target": "sourcedocument", "relation": "references", "confidence": "EXTRACTED", "source_file": "internal/usecase/shipment_usecase.go", "source_location": "L103", "weight": 1.0, "context": "parameter_type"}, {"source": "usecase_shipmentusecase_update", "target": "recipient", "relation": "references", "confidence": "EXTRACTED", "source_file": "internal/usecase/shipment_usecase.go", "source_location": "L103", "weight": 1.0, "context": "parameter_type"}, {"source": "usecase_shipmentusecase_update", "target": "shipmentdetail", "relation": "references", "confidence": "EXTRACTED", "source_file": "internal/usecase/shipment_usecase.go", "source_location": "L103", "weight": 1.0, "context": "parameter_type"}, {"source": "usecase_shipmentusecase_update", "target": "shipmentfinancialsummary", "relation": "references", "confidence": "EXTRACTED", "source_file": "internal/usecase/shipment_usecase.go", "source_location": "L103", "weight": 1.0, "context": "parameter_type"}, {"source": "usecase_shipmentusecase_update", "target": "shipment", "relation": "references", "confidence": "EXTRACTED", "source_file": "internal/usecase/shipment_usecase.go", "source_location": "L103", "weight": 1.0, "context": "return_type"}, {"source": "usecase_shipmentusecase", "target": "usecase_shipmentusecase_delete", "relation": "method", "confidence": "EXTRACTED", "source_file": "internal/usecase/shipment_usecase.go", "source_location": "L157", "weight": 1.0}, {"source": "d_go_api_book_coffee_shop_internal_usecase_shipment_usecase_go", "target": "usecase_shipment_usecase_validateshipmentfields", "relation": "contains", "confidence": "EXTRACTED", "source_file": "internal/usecase/shipment_usecase.go", "source_location": "L193", "weight": 1.0}, {"source": "usecase_shipment_usecase_validateshipmentfields", "target": "sourcedocument", "relation": "references", "confidence": "EXTRACTED", "source_file": "internal/usecase/shipment_usecase.go", "source_location": "L193", "weight": 1.0, "context": "parameter_type"}, {"source": "usecase_shipment_usecase_validateshipmentfields", "target": "recipient", "relation": "references", "confidence": "EXTRACTED", "source_file": "internal/usecase/shipment_usecase.go", "source_location": "L193", "weight": 1.0, "context": "parameter_type"}, {"source": "usecase_shipment_usecase_validateshipmentfields", "target": "shipmentdetail", "relation": "references", "confidence": "EXTRACTED", "source_file": "internal/usecase/shipment_usecase.go", "source_location": "L193", "weight": 1.0, "context": "parameter_type"}, {"source": "usecase_shipmentusecase_create", "target": "usecase_shipment_usecase_validateshipmentfields", "relation": "calls", "context": "call", "confidence": "EXTRACTED", "source_file": "internal/usecase/shipment_usecase.go", "source_location": "L37", "weight": 1.0}, {"source": "usecase_shipmentusecase_update", "target": "usecase_shipment_usecase_validateshipmentfields", "relation": "calls", "context": "call", "confidence": "EXTRACTED", "source_file": "internal/usecase/shipment_usecase.go", "source_location": "L107", "weight": 1.0}, {"source": "usecase_shipmentusecase_update", "target": "usecase_shipmentusecase_getbyid", "relation": "calls", "context": "call", "confidence": "EXTRACTED", "source_file": "internal/usecase/shipment_usecase.go", "source_location": "L118", "weight": 1.0}, {"source": "usecase_shipmentusecase_delete", "target": "usecase_shipmentusecase_getbyid", "relation": "calls", "context": "call", "confidence": "EXTRACTED", "source_file": "internal/usecase/shipment_usecase.go", "source_location": "L169", "weight": 1.0}, {"source": "usecase_shipmentusecase_delete", "target": "usecase_shipmentusecase_update", "relation": "calls", "context": "call", "confidence": "EXTRACTED", "source_file": "internal/usecase/shipment_usecase.go", "source_location": "L178", "weight": 1.0}], "raw_calls": [{"caller_nid": "usecase_shipmentusecase_create", "callee": "generateID", "is_member_call": false, "source_file": "D:\\Go\\api-book-coffee-shop\\internal\\usecase\\shipment_usecase.go", "source_location": "L42"}, {"caller_nid": "usecase_shipmentusecase_create", "callee": "Now", "is_member_call": false, "source_file": "D:\\Go\\api-book-coffee-shop\\internal\\usecase\\shipment_usecase.go", "source_location": "L55"}, {"caller_nid": "usecase_shipmentusecase_create", "callee": "Now", "is_member_call": false, "source_file": "D:\\Go\\api-book-coffee-shop\\internal\\usecase\\shipment_usecase.go", "source_location": "L56"}, {"caller_nid": "usecase_shipmentusecase_create", "callee": "Begin", "is_member_call": true, "source_file": "D:\\Go\\api-book-coffee-shop\\internal\\usecase\\shipment_usecase.go", "source_location": "L59"}, {"caller_nid": "usecase_shipmentusecase_create", "callee": "Rollback", "is_member_call": true, "source_file": "D:\\Go\\api-book-coffee-shop\\internal\\usecase\\shipment_usecase.go", "source_location": "L63"}, {"caller_nid": "usecase_shipmentusecase_create", "callee": "repoFactory", "is_member_call": true, "source_file": "D:\\Go\\api-book-coffee-shop\\internal\\usecase\\shipment_usecase.go", "source_location": "L65"}, {"caller_nid": "usecase_shipmentusecase_create", "callee": "Create", "is_member_call": true, "source_file": "D:\\Go\\api-book-coffee-shop\\internal\\usecase\\shipment_usecase.go", "source_location": "L66"}, {"caller_nid": "usecase_shipmentusecase_create", "callee": "LogEvent", "is_member_call": true, "source_file": "D:\\Go\\api-book-coffee-shop\\internal\\usecase\\shipment_usecase.go", "source_location": "L70"}, {"caller_nid": "usecase_shipmentusecase_create", "callee": "LogRelation", "is_member_call": true, "source_file": "D:\\Go\\api-book-coffee-shop\\internal\\usecase\\shipment_usecase.go", "source_location": "L80"}, {"caller_nid": "usecase_shipmentusecase_create", "callee": "Commit", "is_member_call": true, "source_file": "D:\\Go\\api-book-coffee-shop\\internal\\usecase\\shipment_usecase.go", "source_location": "L86"}, {"caller_nid": "usecase_shipmentusecase_getbyid", "callee": "New", "is_member_call": false, "source_file": "D:\\Go\\api-book-coffee-shop\\internal\\usecase\\shipment_usecase.go", "source_location": "L94"}, {"caller_nid": "usecase_shipmentusecase_getbyid", "callee": "GetByID", "is_member_call": true, "source_file": "D:\\Go\\api-book-coffee-shop\\internal\\usecase\\shipment_usecase.go", "source_location": "L96"}, {"caller_nid": "usecase_shipmentusecase_getall", "callee": "GetAll", "is_member_call": true, "source_file": "D:\\Go\\api-book-coffee-shop\\internal\\usecase\\shipment_usecase.go", "source_location": "L100"}, {"caller_nid": "usecase_shipmentusecase_update", "callee": "New", "is_member_call": false, "source_file": "D:\\Go\\api-book-coffee-shop\\internal\\usecase\\shipment_usecase.go", "source_location": "L105"}, {"caller_nid": "usecase_shipmentusecase_update", "callee": "Begin", "is_member_call": true, "source_file": "D:\\Go\\api-book-coffee-shop\\internal\\usecase\\shipment_usecase.go", "source_location": "L111"}, {"caller_nid": "usecase_shipmentusecase_update", "callee": "Rollback", "is_member_call": true, "source_file": "D:\\Go\\api-book-coffee-shop\\internal\\usecase\\shipment_usecase.go", "source_location": "L115"}, {"caller_nid": "usecase_shipmentusecase_update", "callee": "repoFactory", "is_member_call": true, "source_file": "D:\\Go\\api-book-coffee-shop\\internal\\usecase\\shipment_usecase.go", "source_location": "L117"}, {"caller_nid": "usecase_shipmentusecase_update", "callee": "Now", "is_member_call": false, "source_file": "D:\\Go\\api-book-coffee-shop\\internal\\usecase\\shipment_usecase.go", "source_location": "L137"}, {"caller_nid": "usecase_shipmentusecase_update", "callee": "Update", "is_member_call": true, "source_file": "D:\\Go\\api-book-coffee-shop\\internal\\usecase\\shipment_usecase.go", "source_location": "L139"}, {"caller_nid": "usecase_shipmentusecase_update", "callee": "LogEvent", "is_member_call": true, "source_file": "D:\\Go\\api-book-coffee-shop\\internal\\usecase\\shipment_usecase.go", "source_location": "L143"}, {"caller_nid": "usecase_shipmentusecase_update", "callee": "Commit", "is_member_call": true, "source_file": "D:\\Go\\api-book-coffee-shop\\internal\\usecase\\shipment_usecase.go", "source_location": "L151"}, {"caller_nid": "usecase_shipmentusecase_delete", "callee": "New", "is_member_call": false, "source_file": "D:\\Go\\api-book-coffee-shop\\internal\\usecase\\shipment_usecase.go", "source_location": "L159"}, {"caller_nid": "usecase_shipmentusecase_delete", "callee": "Begin", "is_member_call": true, "source_file": "D:\\Go\\api-book-coffee-shop\\internal\\usecase\\shipment_usecase.go", "source_location": "L162"}, {"caller_nid": "usecase_shipmentusecase_delete", "callee": "Rollback", "is_member_call": true, "source_file": "D:\\Go\\api-book-coffee-shop\\internal\\usecase\\shipment_usecase.go", "source_location": "L166"}, {"caller_nid": "usecase_shipmentusecase_delete", "callee": "repoFactory", "is_member_call": true, "source_file": "D:\\Go\\api-book-coffee-shop\\internal\\usecase\\shipment_usecase.go", "source_location": "L168"}, {"caller_nid": "usecase_shipmentusecase_delete", "callee": "Now", "is_member_call": false, "source_file": "D:\\Go\\api-book-coffee-shop\\internal\\usecase\\shipment_usecase.go", "source_location": "L176"}, {"caller_nid": "usecase_shipmentusecase_delete", "callee": "LogEvent", "is_member_call": true, "source_file": "D:\\Go\\api-book-coffee-shop\\internal\\usecase\\shipment_usecase.go", "source_location": "L182"}, {"caller_nid": "usecase_shipmentusecase_delete", "callee": "Commit", "is_member_call": true, "source_file": "D:\\Go\\api-book-coffee-shop\\internal\\usecase\\shipment_usecase.go", "source_location": "L190"}, {"caller_nid": "usecase_shipment_usecase_validateshipmentfields", "callee": "New", "is_member_call": false, "source_file": "D:\\Go\\api-book-coffee-shop\\internal\\usecase\\shipment_usecase.go", "source_location": "L195"}, {"caller_nid": "usecase_shipment_usecase_validateshipmentfields", "callee": "New", "is_member_call": false, "source_file": "D:\\Go\\api-book-coffee-shop\\internal\\usecase\\shipment_usecase.go", "source_location": "L198"}, {"caller_nid": "usecase_shipment_usecase_validateshipmentfields", "callee": "New", "is_member_call": false, "source_file": "D:\\Go\\api-book-coffee-shop\\internal\\usecase\\shipment_usecase.go", "source_location": "L201"}, {"caller_nid": "usecase_shipment_usecase_validateshipmentfields", "callee": "Contains", "is_member_call": false, "source_file": "D:\\Go\\api-book-coffee-shop\\internal\\usecase\\shipment_usecase.go", "source_location": "L203"}, {"caller_nid": "usecase_shipment_usecase_validateshipmentfields", "callee": "New", "is_member_call": false, "source_file": "D:\\Go\\api-book-coffee-shop\\internal\\usecase\\shipment_usecase.go", "source_location": "L204"}, {"caller_nid": "usecase_shipment_usecase_validateshipmentfields", "callee": "New", "is_member_call": false, "source_file": "D:\\Go\\api-book-coffee-shop\\internal\\usecase\\shipment_usecase.go", "source_location": "L207"}, {"caller_nid": "usecase_shipment_usecase_validateshipmentfields", "callee": "Contains", "is_member_call": false, "source_file": "D:\\Go\\api-book-coffee-shop\\internal\\usecase\\shipment_usecase.go", "source_location": "L209"}, {"caller_nid": "usecase_shipment_usecase_validateshipmentfields", "callee": "New", "is_member_call": false, "source_file": "D:\\Go\\api-book-coffee-shop\\internal\\usecase\\shipment_usecase.go", "source_location": "L210"}, {"caller_nid": "usecase_shipment_usecase_validateshipmentfields", "callee": "New", "is_member_call": false, "source_file": "D:\\Go\\api-book-coffee-shop\\internal\\usecase\\shipment_usecase.go", "source_location": "L213"}, {"caller_nid": "usecase_shipment_usecase_validateshipmentfields", "callee": "New", "is_member_call": false, "source_file": "D:\\Go\\api-book-coffee-shop\\internal\\usecase\\shipment_usecase.go", "source_location": "L216"}, {"caller_nid": "usecase_shipment_usecase_validateshipmentfields", "callee": "New", "is_member_call": false, "source_file": "D:\\Go\\api-book-coffee-shop\\internal\\usecase\\shipment_usecase.go", "source_location": "L219"}, {"caller_nid": "usecase_shipment_usecase_validateshipmentfields", "callee": "New", "is_member_call": false, "source_file": "D:\\Go\\api-book-coffee-shop\\internal\\usecase\\shipment_usecase.go", "source_location": "L222"}, {"caller_nid": "usecase_shipment_usecase_validateshipmentfields", "callee": "Contains", "is_member_call": false, "source_file": "D:\\Go\\api-book-coffee-shop\\internal\\usecase\\shipment_usecase.go", "source_location": "L224"}, {"caller_nid": "usecase_shipment_usecase_validateshipmentfields", "callee": "New", "is_member_call": false, "source_file": "D:\\Go\\api-book-coffee-shop\\internal\\usecase\\shipment_usecase.go", "source_location": "L225"}, {"caller_nid": "usecase_shipment_usecase_validateshipmentfields", "callee": "New", "is_member_call": false, "source_file": "D:\\Go\\api-book-coffee-shop\\internal\\usecase\\shipment_usecase.go", "source_location": "L228"}, {"caller_nid": "usecase_shipment_usecase_validateshipmentfields", "callee": "New", "is_member_call": false, "source_file": "D:\\Go\\api-book-coffee-shop\\internal\\usecase\\shipment_usecase.go", "source_location": "L231"}, {"caller_nid": "usecase_shipment_usecase_validateshipmentfields", "callee": "New", "is_member_call": false, "source_file": "D:\\Go\\api-book-coffee-shop\\internal\\usecase\\shipment_usecase.go", "source_location": "L235"}, {"caller_nid": "usecase_shipment_usecase_validateshipmentfields", "callee": "New", "is_member_call": false, "source_file": "D:\\Go\\api-book-coffee-shop\\internal\\usecase\\shipment_usecase.go", "source_location": "L238"}, {"caller_nid": "usecase_shipment_usecase_validateshipmentfields", "callee": "New", "is_member_call": false, "source_file": "D:\\Go\\api-book-coffee-shop\\internal\\usecase\\shipment_usecase.go", "source_location": "L241"}, {"caller_nid": "usecase_shipment_usecase_validateshipmentfields", "callee": "New", "is_member_call": false, "source_file": "D:\\Go\\api-book-coffee-shop\\internal\\usecase\\shipment_usecase.go", "source_location": "L244"}, {"caller_nid": "usecase_shipment_usecase_validateshipmentfields", "callee": "New", "is_member_call": false, "source_file": "D:\\Go\\api-book-coffee-shop\\internal\\usecase\\shipment_usecase.go", "source_location": "L247"}]}