{"nodes": [{"id": "d_casa_atreides_api_book_coffee_shop_internal_usecase_exercise_usecase_go", "label": "exercise_usecase.go", "file_type": "code", "source_file": "internal/usecase/exercise_usecase.go", "source_location": "L1"}, {"id": "usecase_exerciseusecase", "label": "ExerciseUseCase", "file_type": "code", "source_file": "internal/usecase/exercise_usecase.go", "source_location": "L11"}, {"id": "exerciserepository", "label": "ExerciseRepository", "file_type": "code", "source_file": "internal/usecase/exercise_usecase.go", "source_location": "L20"}, {"id": "usecase_exercise_usecase_newexerciseusecase", "label": "NewExerciseUseCase()", "file_type": "code", "source_file": "internal/usecase/exercise_usecase.go", "source_location": "L23"}, {"id": "usecase_exerciseusecase_create", "label": ".Create()", "file_type": "code", "source_file": "internal/usecase/exercise_usecase.go", "source_location": "L27"}, {"id": "exercise", "label": "Exercise", "file_type": "code", "source_file": "internal/usecase/exercise_usecase.go", "source_location": "L27"}, {"id": "usecase_exerciseusecase_getbyid", "label": ".GetByID()", "file_type": "code", "source_file": "internal/usecase/exercise_usecase.go", "source_location": "L48"}, {"id": "usecase_exerciseusecase_getall", "label": ".GetAll()", "file_type": "code", "source_file": "internal/usecase/exercise_usecase.go", "source_location": "L55"}, {"id": "usecase_exerciseusecase_update", "label": ".Update()", "file_type": "code", "source_file": "internal/usecase/exercise_usecase.go", "source_location": "L59"}, {"id": "usecase_exerciseusecase_delete", "label": ".Delete()", "file_type": "code", "source_file": "internal/usecase/exercise_usecase.go", "source_location": "L84"}, {"id": "usecase_exercise_usecase_validateexercisefields", "label": "validateExerciseFields()", "file_type": "code", "source_file": "internal/usecase/exercise_usecase.go", "source_location": "L91"}], "edges": [{"source": "d_casa_atreides_api_book_coffee_shop_internal_usecase_exercise_usecase_go", "target": "go_pkg_errors", "relation": "imports_from", "confidence": "EXTRACTED", "source_file": "internal/usecase/exercise_usecase.go", "source_location": "L4", "weight": 1.0, "context": "import"}, {"source": "d_casa_atreides_api_book_coffee_shop_internal_usecase_exercise_usecase_go", "target": "go_pkg_time", "relation": "imports_from", "confidence": "EXTRACTED", "source_file": "internal/usecase/exercise_usecase.go", "source_location": "L5", "weight": 1.0, "context": "import"}, {"source": "d_casa_atreides_api_book_coffee_shop_internal_usecase_exercise_usecase_go", "target": "go_pkg_book_coffee_shop_internal_domain", "relation": "imports_from", "confidence": "EXTRACTED", "source_file": "internal/usecase/exercise_usecase.go", "source_location": "L7", "weight": 1.0, "context": "import"}, {"source": "d_casa_atreides_api_book_coffee_shop_internal_usecase_exercise_usecase_go", "target": "go_pkg_book_coffee_shop_internal_repository", "relation": "imports_from", "confidence": "EXTRACTED", "source_file": "internal/usecase/exercise_usecase.go", "source_location": "L8", "weight": 1.0, "context": "import"}, {"source": "d_casa_atreides_api_book_coffee_shop_internal_usecase_exercise_usecase_go", "target": "usecase_exerciseusecase", "relation": "contains", "confidence": "EXTRACTED", "source_file": "internal/usecase/exercise_usecase.go", "source_location": "L11", "weight": 1.0}, {"source": "d_casa_atreides_api_book_coffee_shop_internal_usecase_exercise_usecase_go", "target": "usecase_exerciseusecase", "relation": "contains", "confidence": "EXTRACTED", "source_file": "internal/usecase/exercise_usecase.go", "source_location": "L19", "weight": 1.0}, {"source": "usecase_exerciseusecase", "target": "exerciserepository", "relation": "references", "confidence": "EXTRACTED", "source_file": "internal/usecase/exercise_usecase.go", "source_location": "L20", "weight": 1.0, "context": "field"}, {"source": "d_casa_atreides_api_book_coffee_shop_internal_usecase_exercise_usecase_go", "target": "usecase_exercise_usecase_newexerciseusecase", "relation": "contains", "confidence": "EXTRACTED", "source_file": "internal/usecase/exercise_usecase.go", "source_location": "L23", "weight": 1.0}, {"source": "usecase_exercise_usecase_newexerciseusecase", "target": "exerciserepository", "relation": "references", "confidence": "EXTRACTED", "source_file": "internal/usecase/exercise_usecase.go", "source_location": "L23", "weight": 1.0, "context": "parameter_type"}, {"source": "usecase_exercise_usecase_newexerciseusecase", "target": "usecase_exerciseusecase", "relation": "references", "confidence": "EXTRACTED", "source_file": "internal/usecase/exercise_usecase.go", "source_location": "L23", "weight": 1.0, "context": "return_type"}, {"source": "usecase_exerciseusecase", "target": "usecase_exerciseusecase_create", "relation": "method", "confidence": "EXTRACTED", "source_file": "internal/usecase/exercise_usecase.go", "source_location": "L27", "weight": 1.0}, {"source": "usecase_exerciseusecase_create", "target": "exercise", "relation": "references", "confidence": "EXTRACTED", "source_file": "internal/usecase/exercise_usecase.go", "source_location": "L27", "weight": 1.0, "context": "return_type"}, {"source": "usecase_exerciseusecase", "target": "usecase_exerciseusecase_getbyid", "relation": "method", "confidence": "EXTRACTED", "source_file": "internal/usecase/exercise_usecase.go", "source_location": "L48", "weight": 1.0}, {"source": "usecase_exerciseusecase_getbyid", "target": "exercise", "relation": "references", "confidence": "EXTRACTED", "source_file": "internal/usecase/exercise_usecase.go", "source_location": "L48", "weight": 1.0, "context": "return_type"}, {"source": "usecase_exerciseusecase", "target": "usecase_exerciseusecase_getall", "relation": "method", "confidence": "EXTRACTED", "source_file": "internal/usecase/exercise_usecase.go", "source_location": "L55", "weight": 1.0}, {"source": "usecase_exerciseusecase_getall", "target": "exercise", "relation": "references", "confidence": "EXTRACTED", "source_file": "internal/usecase/exercise_usecase.go", "source_location": "L55", "weight": 1.0, "context": "return_type"}, {"source": "usecase_exerciseusecase", "target": "usecase_exerciseusecase_update", "relation": "method", "confidence": "EXTRACTED", "source_file": "internal/usecase/exercise_usecase.go", "source_location": "L59", "weight": 1.0}, {"source": "usecase_exerciseusecase_update", "target": "exercise", "relation": "references", "confidence": "EXTRACTED", "source_file": "internal/usecase/exercise_usecase.go", "source_location": "L59", "weight": 1.0, "context": "return_type"}, {"source": "usecase_exerciseusecase", "target": "usecase_exerciseusecase_delete", "relation": "method", "confidence": "EXTRACTED", "source_file": "internal/usecase/exercise_usecase.go", "source_location": "L84", "weight": 1.0}, {"source": "d_casa_atreides_api_book_coffee_shop_internal_usecase_exercise_usecase_go", "target": "usecase_exercise_usecase_validateexercisefields", "relation": "contains", "confidence": "EXTRACTED", "source_file": "internal/usecase/exercise_usecase.go", "source_location": "L91", "weight": 1.0}, {"source": "usecase_exerciseusecase_create", "target": "usecase_exercise_usecase_validateexercisefields", "relation": "calls", "context": "call", "confidence": "EXTRACTED", "source_file": "internal/usecase/exercise_usecase.go", "source_location": "L28", "weight": 1.0}, {"source": "usecase_exerciseusecase_update", "target": "usecase_exercise_usecase_validateexercisefields", "relation": "calls", "context": "call", "confidence": "EXTRACTED", "source_file": "internal/usecase/exercise_usecase.go", "source_location": "L63", "weight": 1.0}, {"source": "usecase_exerciseusecase_update", "target": "usecase_exerciseusecase_getbyid", "relation": "calls", "context": "call", "confidence": "EXTRACTED", "source_file": "internal/usecase/exercise_usecase.go", "source_location": "L67", "weight": 1.0}], "raw_calls": [{"caller_nid": "usecase_exerciseusecase_create", "callee": "generateID", "is_member_call": false, "source_file": "D:\\Casa-Atreides\\api-book-coffee-shop\\internal\\usecase\\exercise_usecase.go", "source_location": "L33"}, {"caller_nid": "usecase_exerciseusecase_create", "callee": "Now", "is_member_call": false, "source_file": "D:\\Casa-Atreides\\api-book-coffee-shop\\internal\\usecase\\exercise_usecase.go", "source_location": "L38"}, {"caller_nid": "usecase_exerciseusecase_create", "callee": "Now", "is_member_call": false, "source_file": "D:\\Casa-Atreides\\api-book-coffee-shop\\internal\\usecase\\exercise_usecase.go", "source_location": "L39"}, {"caller_nid": "usecase_exerciseusecase_create", "callee": "Create", "is_member_call": true, "source_file": "D:\\Casa-Atreides\\api-book-coffee-shop\\internal\\usecase\\exercise_usecase.go", "source_location": "L42"}, {"caller_nid": "usecase_exerciseusecase_getbyid", "callee": "New", "is_member_call": false, "source_file": "D:\\Casa-Atreides\\api-book-coffee-shop\\internal\\usecase\\exercise_usecase.go", "source_location": "L50"}, {"caller_nid": "usecase_exerciseusecase_getbyid", "callee": "GetByID", "is_member_call": true, "source_file": "D:\\Casa-Atreides\\api-book-coffee-shop\\internal\\usecase\\exercise_usecase.go", "source_location": "L52"}, {"caller_nid": "usecase_exerciseusecase_getall", "callee": "GetAll", "is_member_call": true, "source_file": "D:\\Casa-Atreides\\api-book-coffee-shop\\internal\\usecase\\exercise_usecase.go", "source_location": "L56"}, {"caller_nid": "usecase_exerciseusecase_update", "callee": "New", "is_member_call": false, "source_file": "D:\\Casa-Atreides\\api-book-coffee-shop\\internal\\usecase\\exercise_usecase.go", "source_location": "L61"}, {"caller_nid": "usecase_exerciseusecase_update", "callee": "Now", "is_member_call": false, "source_file": "D:\\Casa-Atreides\\api-book-coffee-shop\\internal\\usecase\\exercise_usecase.go", "source_location": "L76"}, {"caller_nid": "usecase_exerciseusecase_update", "callee": "Update", "is_member_call": true, "source_file": "D:\\Casa-Atreides\\api-book-coffee-shop\\internal\\usecase\\exercise_usecase.go", "source_location": "L78"}, {"caller_nid": "usecase_exerciseusecase_delete", "callee": "New", "is_member_call": false, "source_file": "D:\\Casa-Atreides\\api-book-coffee-shop\\internal\\usecase\\exercise_usecase.go", "source_location": "L86"}, {"caller_nid": "usecase_exerciseusecase_delete", "callee": "Delete", "is_member_call": true, "source_file": "D:\\Casa-Atreides\\api-book-coffee-shop\\internal\\usecase\\exercise_usecase.go", "source_location": "L88"}, {"caller_nid": "usecase_exercise_usecase_validateexercisefields", "callee": "New", "is_member_call": false, "source_file": "D:\\Casa-Atreides\\api-book-coffee-shop\\internal\\usecase\\exercise_usecase.go", "source_location": "L93"}, {"caller_nid": "usecase_exercise_usecase_validateexercisefields", "callee": "New", "is_member_call": false, "source_file": "D:\\Casa-Atreides\\api-book-coffee-shop\\internal\\usecase\\exercise_usecase.go", "source_location": "L96"}, {"caller_nid": "usecase_exercise_usecase_validateexercisefields", "callee": "New", "is_member_call": false, "source_file": "D:\\Casa-Atreides\\api-book-coffee-shop\\internal\\usecase\\exercise_usecase.go", "source_location": "L99"}, {"caller_nid": "usecase_exercise_usecase_validateexercisefields", "callee": "New", "is_member_call": false, "source_file": "D:\\Casa-Atreides\\api-book-coffee-shop\\internal\\usecase\\exercise_usecase.go", "source_location": "L102"}, {"caller_nid": "usecase_exercise_usecase_validateexercisefields", "callee": "New", "is_member_call": false, "source_file": "D:\\Casa-Atreides\\api-book-coffee-shop\\internal\\usecase\\exercise_usecase.go", "source_location": "L105"}]}